els_utils/__init__.py
els_utils/els.py
els_utils/explain_utils.py
els_utils/response.py
els_utils/results.py
els_utils/types.py
els_utils/version.py
els_utils-0.3.9.dist-info/METADATA
els_utils-0.3.9.dist-info/WHEEL
els_utils-0.3.9.dist-info/RECORD
