Metadata-Version: 2.4
Name: els-utils
Version: 0.3.9
Summary: A simple wrapper for Elasticsearch tool
Author-email: Anupong Wannakrairot <anuponwa@scg.com>
Requires-Python: >=3.9
Requires-Dist: pandas>=2.0.0
Requires-Dist: requests>=2.32.3
